discrete_distribution_network/__init__.py
discrete_distribution_network/ddn.py
discrete_distribution_network-0.2.3.dist-info/METADATA
discrete_distribution_network-0.2.3.dist-info/WHEEL
discrete_distribution_network-0.2.3.dist-info/licenses/LICENSE
discrete_distribution_network-0.2.3.dist-info/RECORD
