Metadata-Version: 2.4
Name: discrete-distribution-network
Version: 0.2.3
Summary: Discrete Distribution Network
Project-URL: Homepage, https://pypi.org/project/discrete-distribution-network/
Project-URL: Repository, https://github.com/lucidrains/discrete-distribution-network
Author-email: Phil Wang <lucidrains@gmail.com>
License: MIT License
License-File: LICENSE
Keywords: artificial intelligence,deep learning,generative modeling
Classifier: Development Status :: 4 - Beta
Classifier: Intended Audience :: Developers
Classifier: License :: OSI Approved :: MIT License
Classifier: Programming Language :: Python :: 3.9
Classifier: Topic :: Scientific/Engineering :: Artificial Intelligence
Requires-Python: >=3.9
Requires-Dist: accelerate
Requires-Dist: einops>=0.8.1
Requires-Dist: ema-pytorch
Requires-Dist: torch>=2.4
Requires-Dist: torchvision
Requires-Dist: x-mlps-pytorch>=0.1.0
Provides-Extra: examples
Provides-Extra: test
Requires-Dist: pytest; extra == 'test'
